{
  "type": "FeatureCollection",
  "features": [
    {
      "type": "Feature",
      "geometry": {
        "type": "Point",
        "coordinates": [
          2.3522,
          48.8566
        ]
      },
      "properties": {
        "time": "1993-01-01",
        "popup": "Jan-R\u00e9mi FROMENTIN<br>\u00c2ge : 29<br>Paris",
        "Nom": "FROMENTIN",
        "Pr\u00e9nom": "Jan-R\u00e9mi",
        "\u00c2ge": 29,
        "Ann\u00e9e": 1993
      }
    },
    {
      "type": "Feature",
      "geometry": {
        "type": "Point",
        "coordinates": [
          2.3522,
          48.8566
        ]
      },
      "properties": {
        "time": "1993-01-01",
        "popup": "Laure FROMENTIN<br>\u00c2ge : 27<br>Paris",
        "Nom": "FROMENTIN",
        "Pr\u00e9nom": "Laure",
        "\u00c2ge": 27,
        "Ann\u00e9e": 1993
      }
    },
    {
      "type": "Feature",
      "geometry": {
        "type": "Point",
        "coordinates": [
          5.9178,
          45.5646
        ]
      },
      "properties": {
        "time": "1993-01-01",
        "popup": "Claude FELMAN<br>\u00c2ge : 55<br>Chambery",
        "Nom": "FELMAN",
        "Pr\u00e9nom": "Claude",
        "\u00c2ge": 55,
        "Ann\u00e9e": 1993
      }
    },
    {
      "type": "Feature",
      "geometry": {
        "type": "Point",
        "coordinates": [
          2.3522,
          48.8566
        ]
      },
      "properties": {
        "time": "1995-01-01",
        "popup": "Jan-R\u00e9mi FROMENTIN<br>\u00c2ge : 31<br>Paris",
        "Nom": "FROMENTIN",
        "Pr\u00e9nom": "Jan-R\u00e9mi",
        "\u00c2ge": 31,
        "Ann\u00e9e": 1995
      }
    },
    {
      "type": "Feature",
      "geometry": {
        "type": "Point",
        "coordinates": [
          2.3522,
          48.8566
        ]
      },
      "properties": {
        "time": "1995-01-01",
        "popup": "Laure FROMENTIN<br>\u00c2ge : 29<br>Paris",
        "Nom": "FROMENTIN",
        "Pr\u00e9nom": "Laure",
        "\u00c2ge": 29,
        "Ann\u00e9e": 1995
      }
    },
    {
      "type": "Feature",
      "geometry": {
        "type": "Point",
        "coordinates": [
          1.9093,
          47.9029
        ]
      },
      "properties": {
        "time": "1995-01-01",
        "popup": "Claude FELMAN<br>\u00c2ge : 57<br>Orl\u00e9ans",
        "Nom": "FELMAN",
        "Pr\u00e9nom": "Claude",
        "\u00c2ge": 57,
        "Ann\u00e9e": 1995
      }
    },
    {
      "type": "Feature",
      "geometry": {
        "type": "Point",
        "coordinates": [
          5.7245,
          45.1885
        ]
      },
      "properties": {
        "time": "1999-01-01",
        "popup": "Jan-R\u00e9mi FROMENTIN<br>\u00c2ge : 36<br>Grenoble",
        "Nom": "FROMENTIN",
        "Pr\u00e9nom": "Jan-R\u00e9mi",
        "\u00c2ge": 36,
        "Ann\u00e9e": 1999
      }
    },
    {
      "type": "Feature",
      "geometry": {
        "type": "Point",
        "coordinates": [
          5.7245,
          45.1885
        ]
      },
      "properties": {
        "time": "1999-01-01",
        "popup": "Laure FROMENTIN<br>\u00c2ge : 33<br>Grenoble",
        "Nom": "FROMENTIN",
        "Pr\u00e9nom": "Laure",
        "\u00c2ge": 33,
        "Ann\u00e9e": 1999
      }
    },
    {
      "type": "Feature",
      "geometry": {
        "type": "Point",
        "coordinates": [
          1.9093,
          47.9029
        ]
      },
      "properties": {
        "time": "1999-01-01",
        "popup": "Claude FELMAN<br>\u00c2ge : 61<br>Orl\u00e9ans",
        "Nom": "FELMAN",
        "Pr\u00e9nom": "Claude",
        "\u00c2ge": 61,
        "Ann\u00e9e": 1999
      }
    },
    {
      "type": "Feature",
      "geometry": {
        "type": "Point",
        "coordinates": [
          4.8357,
          45.764
        ]
      },
      "properties": {
        "time": "2003-01-01",
        "popup": "Jan-R\u00e9mi FROMENTIN<br>\u00c2ge : 40<br>Lyon",
        "Nom": "FROMENTIN",
        "Pr\u00e9nom": "Jan-R\u00e9mi",
        "\u00c2ge": 40,
        "Ann\u00e9e": 2003
      }
    },
    {
      "type": "Feature",
      "geometry": {
        "type": "Point",
        "coordinates": [
          5.3698,
          43.2965
        ]
      },
      "properties": {
        "time": "2003-01-01",
        "popup": "Laure FROMENTIN<br>\u00c2ge : 37<br>Marseille",
        "Nom": "FROMENTIN",
        "Pr\u00e9nom": "Laure",
        "\u00c2ge": 37,
        "Ann\u00e9e": 2003
      }
    },
    {
      "type": "Feature",
      "geometry": {
        "type": "Point",
        "coordinates": [
          3.2158,
          43.3442
        ]
      },
      "properties": {
        "time": "2003-01-01",
        "popup": "Claude FELMAN<br>\u00c2ge : 65<br>B\u00e9ziers",
        "Nom": "FELMAN",
        "Pr\u00e9nom": "Claude",
        "\u00c2ge": 65,
        "Ann\u00e9e": 2003
      }
    }
  ]
}